{
  "_fv": 57,
  "_type": "tag",
  "definition": {
    "type": "Items",
    "items": [
      {
        "value": "CUSTOM:Ulbiseaf"
      },
      {
        "value": "CUSTOM:Crewanolla"
      },
      {
        "value": "CUSTOM:Ceblum"
      },
      {
        "value": "CUSTOM:Rinyot"
      },
      {
        "value": "CUSTOM:FloweringWiltumVines"
      }
    ],
    "blocks": [],
    "functions": [],
    "entities": [],
    "biomes": [],
    "damageTypes": [],
    "name": "blue_dye_plants",
    "namespace": "mod"
  }
}