{
	"format_version": "1.12.0",
	"minecraft:geometry": [
		{
			"description": {
				"identifier": "geometry.culafite_shroomer",
				"texture_width": 64,
				"texture_height": 64,
				"visible_bounds_width": 2,
				"visible_bounds_height": 2.5,
				"visible_bounds_offset": [0, 0.75, 0]
			},
			"bones": [
				{
					"name": "Everything",
					"pivot": [2, 3, 0]
				},
				{
					"name": "Body",
					"parent": "Everything",
					"pivot": [0, 4, 0],
					"cubes": [
						{"origin": [-3, 3, -3], "size": [6, 8, 6], "uv": [0, 18]}
					]
				},
				{
					"name": "Eyelids",
					"parent": "Body",
					"pivot": [0, 7.25, -2.5]
				},
				{
					"name": "rightEyelid",
					"parent": "Eyelids",
					"pivot": [2, 7.25, -2.5],
					"cubes": [
						{"origin": [1, 6.75, -3], "size": [2, 1, 1], "inflate": 0.25, "uv": [0, 22]}
					]
				},
				{
					"name": "leftEyelid",
					"parent": "Eyelids",
					"pivot": [-2, 7.25, -2.5],
					"cubes": [
						{"origin": [-3, 6.75, -3], "size": [2, 1, 1], "inflate": 0.25, "uv": [0, 22], "mirror": true}
					]
				},
				{
					"name": "Petals",
					"parent": "Body",
					"pivot": [0, 10, -3]
				},
				{
					"name": "frontPetal",
					"parent": "Petals",
					"pivot": [0, 10, -3],
					"rotation": [-45, 0, 0],
					"cubes": [
						{"origin": [-2.5, 6, -3], "size": [5, 4, 0], "uv": [0, 0]}
					]
				},
				{
					"name": "leftPetal",
					"parent": "Petals",
					"pivot": [-3, 10, 0],
					"cubes": [
						{"origin": [-3, 6, -2.5], "size": [0, 4, 5], "pivot": [-3, 10, 0], "rotation": [0, 0, 45], "uv": [0, -5]}
					]
				},
				{
					"name": "backPetal",
					"parent": "Petals",
					"pivot": [0, 10, 3],
					"rotation": [45, 0, 0],
					"cubes": [
						{"origin": [-2.5, 6, 3], "size": [5, 4, 0], "uv": [0, 0]}
					]
				},
				{
					"name": "rightPetal",
					"parent": "Petals",
					"pivot": [3, 10, 0],
					"cubes": [
						{"origin": [3, 6, -2.5], "size": [0, 4, 5], "pivot": [3, 10, 0], "rotation": [0, 0, -45], "uv": [0, -5], "mirror": true}
					]
				},
				{
					"name": "Roots",
					"parent": "Body",
					"pivot": [0, 10, -3],
					"cubes": [
						{"origin": [-3, 0, 0], "size": [6, 3, 0], "pivot": [0, 1.5, 0], "rotation": [0, 45, 0], "uv": [14, 35]},
						{"origin": [-3, 0, 0], "size": [6, 3, 0], "pivot": [0, 1.5, 0], "rotation": [0, -45, 0], "uv": [14, 35]}
					]
				},
				{
					"name": "Cap",
					"parent": "Body",
					"pivot": [0, 12, 0],
					"cubes": [
						{"origin": [-7, 11, -7], "size": [14, 4, 14], "uv": [0, 0]}
					]
				},
				{
					"name": "Shroomlight",
					"parent": "Cap",
					"pivot": [0, 17, 0],
					"cubes": [
						{"origin": [-7, 15, 0], "size": [14, 4, 0], "pivot": [0, 17, 0], "rotation": [0, -45, 0], "uv": [28, 18]},
						{"origin": [-7, 15, 0], "size": [14, 4, 0], "pivot": [0, 17, 0], "rotation": [0, -135, 0], "uv": [28, 18]}
					]
				},
				{
					"name": "leftArm",
					"parent": "Everything",
					"pivot": [-2.5, 2.5, -2.5],
					"rotation": [0, -45, 0]
				},
				{
					"name": "leftArm2",
					"parent": "leftArm",
					"pivot": [-2.5, 2.5, -2.5],
					"rotation": [0, 0, -25],
					"cubes": [
						{"origin": [-5.5, 1, -4], "size": [4, 3, 3], "uv": [0, 32]},
						{"origin": [-6.5, 2, -4.5], "size": [4, 0, 4], "uv": [-4, 10]}
					]
				},
				{
					"name": "rightArm",
					"parent": "Everything",
					"pivot": [2.5, 2.5, -2.5],
					"rotation": [0, 45, 0]
				},
				{
					"name": "rightArm2",
					"parent": "rightArm",
					"pivot": [2.5, 2.5, -2.5],
					"rotation": [0, 0, 25],
					"cubes": [
						{"origin": [1.5, 1, -4], "size": [4, 3, 3], "uv": [0, 32], "mirror": true},
						{"origin": [2.5, 2, -4.5], "size": [4, 0, 4], "uv": [-4, 10], "mirror": true}
					]
				},
				{
					"name": "leftLeg",
					"parent": "Everything",
					"pivot": [-2.5, 2.5, 2.5],
					"rotation": [0, 45, 0]
				},
				{
					"name": "leftLeg2",
					"parent": "leftLeg",
					"pivot": [-2.5, 2.5, 2.5],
					"rotation": [0, 0, -25],
					"cubes": [
						{"origin": [-5.5, 1, 1], "size": [4, 3, 3], "uv": [0, 32]},
						{"origin": [-6.5, 2, 0.5], "size": [4, 0, 4], "uv": [-4, 10]}
					]
				},
				{
					"name": "rightLeg",
					"parent": "Everything",
					"pivot": [2.5, 2.5, 2.5],
					"rotation": [0, -45, 0]
				},
				{
					"name": "rightLeg2",
					"parent": "rightLeg",
					"pivot": [2.5, 2.5, 2.5],
					"rotation": [0, 0, 25],
					"cubes": [
						{"origin": [1.5, 1, 1], "size": [4, 3, 3], "uv": [0, 32], "mirror": true},
						{"origin": [2.5, 2, 0.5], "size": [4, 0, 4], "uv": [-4, 10], "mirror": true}
					]
				}
			]
		}
	]
}